roboticstoolbox/__init__.py
roboticstoolbox/fknm.cp312-win_amd64.pyd
roboticstoolbox/frne.cp312-win_amd64.pyd
roboticstoolbox/backends/Connector.py
roboticstoolbox/backends/__init__.py
roboticstoolbox/backends/PyPlot/EllipsePlot.py
roboticstoolbox/backends/PyPlot/PyPlot.py
roboticstoolbox/backends/PyPlot/PyPlot2.py
roboticstoolbox/backends/PyPlot/RobotPlot.py
roboticstoolbox/backends/PyPlot/RobotPlot2.py
roboticstoolbox/backends/PyPlot/__init__.py
roboticstoolbox/backends/swift/__init__.py
roboticstoolbox/bin/__init__.py
roboticstoolbox/bin/rtbtool.py
roboticstoolbox/blocks/__init__.py
roboticstoolbox/blocks/arm.py
roboticstoolbox/blocks/mobile.py
roboticstoolbox/blocks/quad_model.py
roboticstoolbox/blocks/spatial.py
roboticstoolbox/blocks/uav.py
roboticstoolbox/core/fknm.cpp
roboticstoolbox/core/fknm.h
roboticstoolbox/core/frne.c
roboticstoolbox/core/frne.h
roboticstoolbox/core/ik.cpp
roboticstoolbox/core/ik.h
roboticstoolbox/core/linalg.cpp
roboticstoolbox/core/linalg.h
roboticstoolbox/core/methods.cpp
roboticstoolbox/core/methods.h
roboticstoolbox/core/ne.c
roboticstoolbox/core/structs.cpp
roboticstoolbox/core/structs.h
roboticstoolbox/core/vmath.c
roboticstoolbox/core/vmath.h
roboticstoolbox/core/Eigen/Cholesky
roboticstoolbox/core/Eigen/CholmodSupport
roboticstoolbox/core/Eigen/Core
roboticstoolbox/core/Eigen/Dense
roboticstoolbox/core/Eigen/Eigen
roboticstoolbox/core/Eigen/Eigenvalues
roboticstoolbox/core/Eigen/Geometry
roboticstoolbox/core/Eigen/Householder
roboticstoolbox/core/Eigen/IterativeLinearSolvers
roboticstoolbox/core/Eigen/Jacobi
roboticstoolbox/core/Eigen/KLUSupport
roboticstoolbox/core/Eigen/LU
roboticstoolbox/core/Eigen/MetisSupport
roboticstoolbox/core/Eigen/OrderingMethods
roboticstoolbox/core/Eigen/PaStiXSupport
roboticstoolbox/core/Eigen/PardisoSupport
roboticstoolbox/core/Eigen/QR
roboticstoolbox/core/Eigen/QtAlignedMalloc
roboticstoolbox/core/Eigen/SPQRSupport
roboticstoolbox/core/Eigen/SVD
roboticstoolbox/core/Eigen/Sparse
neura_roboticstoolbox-0.0.3.dist-info/LICENSE
neura_roboticstoolbox-0.0.3.dist-info/METADATA
neura_roboticstoolbox-0.0.3.dist-info/WHEEL
neura_roboticstoolbox-0.0.3.dist-info/entry_points.txt
neura_roboticstoolbox-0.0.3.dist-info/top_level.txt
neura_roboticstoolbox-0.0.3.dist-info/RECORD
