Metadata-Version: 2.1
Name: neura-roboticstoolbox
Version: 0.0.3
Summary: roboticstoolbox-python with Maira7M
Author-email: Jesse Haviland <j.haviland@qut.edu.au>, Peter Corke <rvc@petercorke.com>, Jens Temminghoff <jens.temminghoff@neura-robotics.com>
License: MIT License
Project-URL: homepage, https://github.com/JTem/neura_robotics_toolbox
Project-URL: documentation, https://petercorke.github.io/robotics-toolbox-python/
Project-URL: repository, https://github.com/JTem/neura_robotics_toolbox
Keywords: python,robotics,robotics-toolbox,kinematics,dynamics,motion-planning,trajectory-generation,jacobian,hessian,control,simulation,robot-manipulator,mobile-robot
Classifier: Development Status :: 5 - Production/Stable
Classifier: Intended Audience :: Developers
Classifier: License :: OSI Approved :: MIT License
Classifier: Programming Language :: Python :: 3.7
Classifier: Programming Language :: Python :: 3.8
Classifier: Programming Language :: Python :: 3.9
Classifier: Programming Language :: Python :: 3.10
Classifier: Programming Language :: Python :: 3.11
Requires-Python: >=3.7
License-File: LICENSE
Requires-Dist: numpy >=1.17.4
Requires-Dist: spatialmath-python >=1.1.5
Requires-Dist: spatialgeometry >=1.0.0
Requires-Dist: pgraph-python
Requires-Dist: scipy
Requires-Dist: matplotlib
Requires-Dist: ansitable
Requires-Dist: neura-swift >=0.0.2
Requires-Dist: neura-rtb-data
Requires-Dist: progress
Requires-Dist: typing-extensions
Provides-Extra: collision
Requires-Dist: pybullet ; extra == 'collision'
Provides-Extra: dev
Requires-Dist: black ; extra == 'dev'
Requires-Dist: pytest ; extra == 'dev'
Requires-Dist: pytest-cov ; extra == 'dev'
Requires-Dist: flake8 ; extra == 'dev'
Requires-Dist: pyyaml ; extra == 'dev'
Requires-Dist: sympy ; extra == 'dev'
Requires-Dist: qpsolvers ; extra == 'dev'
Requires-Dist: quadprog ; extra == 'dev'
Requires-Dist: pybullet ; extra == 'dev'
Requires-Dist: bdsim ; extra == 'dev'
Provides-Extra: docs
Requires-Dist: sphinx ; extra == 'docs'
Requires-Dist: sphinx-rtd-theme ; extra == 'docs'
Requires-Dist: sphinx-autorun ; extra == 'docs'
Requires-Dist: sphinx-autodoc-typehints ; extra == 'docs'
Requires-Dist: sphinx-favicon ; extra == 'docs'
